Metadata-Version: 2.4
Name: iflow-mcp_dart-mcp
Version: 0.1.1
Summary: Add your description here
Requires-Python: >=3.10
Requires-Dist: httpx>=0.28.1
Requires-Dist: mcp[cli]>=1.6.0
Requires-Dist: python-dotenv>=1.0.0
